noob-0.0.9999999.dist-info/METADATA
noob-0.0.9999999.dist-info/WHEEL
noob-0.0.9999999.dist-info/entry_points.txt
noob-0.0.9999999.dist-info/licenses/LICENSE
noob/__init__.py
noob/important.txt
noob/tube.py
noob-0.0.9999999.dist-info/RECORD
