Metadata-Version: 2.1
Name: noob
Version: 0.0.9999999
Summary: Default template for PDM package
Author-Email: raymondwjang <ray0815@ucla.edu>, sneakers-the-rat <sneakers-the-rat@protonmail.com>
License: MIT
Requires-Python: >=3.11
